tool.py
zcytestlib/__init__.py
zcytestlib/zcylibone.py
zcytestlib-1.0.1.dist-info/LICENSE.txt
zcytestlib-1.0.1.dist-info/METADATA
zcytestlib-1.0.1.dist-info/WHEEL
zcytestlib-1.0.1.dist-info/top_level.txt
zcytestlib-1.0.1.dist-info/RECORD
