Metadata-Version: 2.1
Name: zcytestlib
Version: 1.0.1
Summary: this is a zcy demo lib 
Home-page: https://github.com/aheake/zcyTest
Author: ZCY
Author-email: zcyang098@163.com
License: MIT
License-File: LICENSE.txt
